{"streams":[{"name":"720p | ThePirateBay (90S)","description":"FRIENDS - SEASON 1-10 - 720P - MP4\nCalidad: 720p | Tamaño: 200.25 MB | Proveedor: ThePirateBay | Seeders: 90 | Peers: 27","infoHash":"ffccb399778ec56d7e6a1ec9954c1be56df260bf","sources":["tracker:udp://tracker.opentrackr.org:1337/announce","tracker:udp://tracker.openbittorrent.com:6969/announce","tracker:udp://9.rarbg.to:2710/announce","tracker:udp://exodus.desync.com:6969/announce"],"behaviorHints":{"bingeGroup":"magnet-ffccb399778ec56d7e6a1ec9954c1be56df260bf","countryWhitelist":["US","GB","CA","AU","DE","FR","ES","IT","NL","SE","NO","DK","FI"],"videoSize":209977344,"filename":"Friends - 01x01 -The One Where Monica Gets A Roommate.mp4"}}],"cacheMaxAge":3600}
